tuparser/__init__.py
tuparser/constants.py
tuparser/parser.py
tuparser/utils.py
tuparser/validator.py
tuparser-1.0.0.dist-info/LICENSE
tuparser-1.0.0.dist-info/METADATA
tuparser-1.0.0.dist-info/WHEEL
tuparser-1.0.0.dist-info/top_level.txt
tuparser-1.0.0.dist-info/RECORD
