Metadata-Version: 2.1
Name: tuparser
Version: 1.0.0
Summary: A flexible module for building custom parsers for the Telegraph website
Home-page: https://github.com/zombyacoff/tu-parser
Author: zombyacoff
Author-email: zombyacoff@gmail.com
Keywords: parser scraper parser-api telegraph telegraph-api
Classifier: License :: OSI Approved :: MIT License
Classifier: Operating System :: OS Independent
Classifier: Programming Language :: Python :: 3.12
Requires-Python: >=3.12
License-File: LICENSE
Requires-Dist: aiohttp
Requires-Dist: bs4
Requires-Dist: PyYaml
Requires-Dist: termcolor
Requires-Dist: tqdm
